<root><Wagen Mixnummer="13844782" Mixmoment="2014-10-17T06:47:41"><WagenType>P2x</WagenType><Uitvoering>R-Line</Uitvoering><Motor>D2</Motor><Kleur>Zilver</Kleur><Bekleding>Mixed Stof</Bekleding><KleurInterieur>Zwart</KleurInterieur><Maatsysteem>US</Maatsysteem><Taal>Spaans</Taal><Onderdelen><Onderdeel Categorie="Glovebox"/><Onderdeel Categorie="HeaterButton"/><Onderdeel Categorie="TopCover"/><Onderdeel Categorie="HeaterButton"/><Onderdeel Categorie="Airbag"/><Onderdeel Categorie="Airco"/><Onderdeel Categorie="AirbagSticker"/><Onderdeel Categorie="Alarmknop"/><Onderdeel Categorie="Vizor"/></Onderdelen></Wagen></root>